shadowlib/__init__.py
shadowlib/client.py
shadowlib/globals.py
shadowlib/_internal/api.py
shadowlib/_internal/cache_manager.py
shadowlib/_internal/cleanup.py
shadowlib/_internal/enums.py
shadowlib/_internal/msgpack_protocol.py
shadowlib/_internal/query_builder.py
shadowlib/_internal/query_builder.pyi
shadowlib/_internal/cache/__init__.py
shadowlib/_internal/cache/event_cache.py
shadowlib/_internal/cache/state_builder.py
shadowlib/_internal/events/__init__.py
shadowlib/_internal/events/channels.py
shadowlib/_internal/events/consumer.py
shadowlib/_internal/resources/__init__.py
shadowlib/_internal/resources/objects.py
shadowlib/_internal/resources/objects.pyi
shadowlib/_internal/resources/varps.py
shadowlib/_internal/resources/varps.pyi
shadowlib/_internal/scraper/__init__.py
shadowlib/_internal/scraper/proxy_generator.py
shadowlib/_internal/scraper/scraper.py
shadowlib/_internal/updater/__init__.py
shadowlib/_internal/updater/__main__.py
shadowlib/_internal/updater/api.py
shadowlib/_internal/updater/main.py
shadowlib/_internal/updater/resources.py
shadowlib/_internal/visualizer/__init__.py
shadowlib/_internal/visualizer/capture.py
shadowlib/_internal/visualizer/visualizer.py
shadowlib/_internal/visualizer/window.py
shadowlib/input/__init__.py
shadowlib/input/drawing.py
shadowlib/input/keyboard.py
shadowlib/input/mouse.py
shadowlib/input/runelite.py
shadowlib/interactions/__init__.py
shadowlib/interactions/menu.py
shadowlib/interfaces/__init__.py
shadowlib/interfaces/bank.py
shadowlib/interfaces/fairy_ring.py
shadowlib/navigation/__init__.py
shadowlib/navigation/pathfinder.py
shadowlib/navigation/walker.py
shadowlib/player/__init__.py
shadowlib/player/player.py
shadowlib/tabs/__init__.py
shadowlib/tabs/account.py
shadowlib/tabs/combat.py
shadowlib/tabs/emotes.py
shadowlib/tabs/equipment.py
shadowlib/tabs/friends.py
shadowlib/tabs/grouping.py
shadowlib/tabs/inventory.py
shadowlib/tabs/logout.py
shadowlib/tabs/magic.py
shadowlib/tabs/music.py
shadowlib/tabs/prayer.py
shadowlib-3.4.0.dist-info/licenses/LICENSE
shadowlib-3.4.0.dist-info/METADATA
shadowlib-3.4.0.dist-info/WHEEL
shadowlib-3.4.0.dist-info/top_level.txt
shadowlib-3.4.0.dist-info/RECORD
