Metadata-Version: 2.4
Name: shadowlib
Version: 3.4.0
Summary: OSRS Bot Development SDK with game-native structure
Author: ShadowBot Team
License: MIT
Project-URL: Homepage, https://github.com/ShadowLib/shadowlib
Project-URL: Repository, https://github.com/ShadowLib/shadowlib
Project-URL: Issues, https://github.com/ShadowLib/shadowlib/issues
Keywords: osrs,runescape,bot,automation,sdk
Classifier: Development Status :: 3 - Alpha
Classifier: Intended Audience :: Developers
Classifier: License :: OSI Approved :: MIT License
Classifier: Programming Language :: Python :: 3
Classifier: Programming Language :: Python :: 3.12
Classifier: Topic :: Games/Entertainment
Classifier: Topic :: Software Development :: Libraries :: Python Modules
Requires-Python: >=3.12
License-File: LICENSE
Requires-Dist: msgpack>=1.0.0
Requires-Dist: inotify-simple>=1.3.5
Requires-Dist: pyautogui>=0.9.54
Requires-Dist: python-xlib>=0.33
Requires-Dist: Pillow>=10.0.0
Requires-Dist: numpy>=1.26.0
Provides-Extra: dev
Requires-Dist: pytest>=7.4.0; extra == "dev"
Requires-Dist: pytest-cov>=4.1.0; extra == "dev"
Requires-Dist: pytest-asyncio>=0.21.0; extra == "dev"
Requires-Dist: ruff>=0.8.4; extra == "dev"
Requires-Dist: pre-commit>=3.5.0; extra == "dev"
Requires-Dist: mypy>=1.7.0; extra == "dev"
Dynamic: license-file
